source_microsoft_dataverse/__init__.py
source_microsoft_dataverse/dataverse.py
source_microsoft_dataverse/run.py
source_microsoft_dataverse/source.py
source_microsoft_dataverse/spec.yaml
source_microsoft_dataverse/streams.py
airbyte_source_microsoft_dataverse-0.1.32.dist-info/METADATA
airbyte_source_microsoft_dataverse-0.1.32.dist-info/WHEEL
airbyte_source_microsoft_dataverse-0.1.32.dist-info/entry_points.txt
airbyte_source_microsoft_dataverse-0.1.32.dist-info/RECORD
